{
  "project_info": {
    "project_number": "865986715215",
    "project_id": "bookstore-e9f45",
    "storage_bucket": "bookstore-e9f45.firebasestorage.app"
  },
  "client": [
    {
      "client_info": {
        "mobilesdk_app_id": "1:865986715215:android:70004d9288c1ff8139943a",
        "android_client_info": {
          "package_name": "com.example.bookstoreapp"
        }
      },
      "oauth_client": [],
      "api_key": [
        {
          "current_key": "AIzaSyC4w1lv-Vi0DBJCzXmuARyd0sv4MjaT1H4"
        }
      ],
      "services": {
        "appinvite_service": {
          "other_platform_oauth_client": []
        }
      }
    }
  ],
  "configuration_version": "1"
}